[{"__type__":"cc.SpriteFrame","content":{"name":"flame_static","texture":"24U5H9H79KL6PRZWSJVuAe","rect":[0,0,249,39],"offset":[0,0],"originalSize":[249,39],"capInsets":[0,0,0,0]}},{"__type__":"cc.SpriteFrame","content":{"name":"buildig","texture":"feYJOOedVLk4Gd/eXv91wO","rect":[25,0,654,278],"offset":[-8,0],"originalSize":[720,278],"capInsets":[0,0,0,0]}},{"__type__":"cc.SpriteFrame","content":{"name":" mountain","texture":"29/a4I6wRL4b4Z+XyurKMf","rect":[0,24,720,216],"offset":[0,-12],"originalSize":[720,240],"capInsets":[0,0,0,0]}},{"__type__":"cc.SpriteFrame","content":{"name":"light_static","texture":"9doLTyM/RPBozthBbx67cI","rect":[0,4,359,97],"offset":[0,-2],"originalSize":[359,101],"capInsets":[0,0,0,0]}},{"__type__":"cc.SpriteFrame","content":{"name":"stage_bg","texture":"b2l1aJ+rBCUa2BAqesoNVz","rect":[0,0,360,485],"offset":[0,0],"originalSize":[360,485],"capInsets":[0,0,0,0]}},{"__type__":"cc.SpriteFrame","content":{"name":"platform","texture":"eas4ZEOaNHl7W5UFWBbtuK","rect":[0,0,274,61],"offset":[0,0],"originalSize":[274,61],"capInsets":[0,0,0,0]}},{"__type__":"cc.SpriteFrame","content":{"name":" aircraft","texture":"1cpDsyvQ1BfZPNfO8/lGIK","rect":[0,0,75,36],"offset":[0,0],"originalSize":[75,36],"capInsets":[0,0,0,0]}},{"__type__":"cc.SpriteFrame","content":{"name":" planet","texture":"428bvFetZDV4gv7GV5Nx2Y","rect":[0,0,59,38],"offset":[0,0],"originalSize":[59,38],"capInsets":[0,0,0,0]}},{"__type__":"cc.SpriteFrame","content":{"name":"circle","texture":"64GqJtRf5Lspg/bgZiM84K","rect":[0,0,720,176],"offset":[0,0],"originalSize":[720,176],"capInsets":[0,0,0,0]}},{"__type__":"cc.SpriteFrame","content":{"name":" machine","texture":"a2uhSkfUFLB4hUPYD3cN+Y","rect":[0,0,720,252],"offset":[0,0],"originalSize":[720,252],"capInsets":[0,0,0,0]}}]